dictionary/__init__.py
dictionary/dictionary.py
adeem_adil_khatri_very_simple_dictionary-2.0.1.dist-info/METADATA
adeem_adil_khatri_very_simple_dictionary-2.0.1.dist-info/WHEEL
adeem_adil_khatri_very_simple_dictionary-2.0.1.dist-info/top_level.txt
adeem_adil_khatri_very_simple_dictionary-2.0.1.dist-info/RECORD
